zoxy/__init__.py
zoxy/__main__.py
zoxy/cli.py
zoxy/http.py
zoxy/server.py
zoxy/typings.py
zoxy-0.0.5.dist-info/LICENSE
zoxy-0.0.5.dist-info/METADATA
zoxy-0.0.5.dist-info/WHEEL
zoxy-0.0.5.dist-info/entry_points.txt
zoxy-0.0.5.dist-info/top_level.txt
zoxy-0.0.5.dist-info/RECORD
