Metadata-Version: 2.1
Name: zoxy
Version: 0.0.5
Summary: python proxy
Home-page: https://github.com/zondatw/zoxy
Author: Zonda Yang
Author-email: u226699@gmail.com
License: MIT
Keywords: proxy http
Platform: UNKNOWN
Classifier: Programming Language :: Python :: 3
Classifier: License :: OSI Approved :: MIT License
Requires-Python: >=3.7
Requires-Dist: mypy ; python_version <= "3.7"
